MANIFEST.in
README.rst
setup.py
django_reporting.egg-info/PKG-INFO
django_reporting.egg-info/SOURCES.txt
django_reporting.egg-info/dependency_links.txt
django_reporting.egg-info/not-zip-safe
django_reporting.egg-info/requires.txt
django_reporting.egg-info/top_level.txt
reporting/__init__.py
reporting/base.py
reporting/filterspecs.py
reporting/site.py
reporting/urls.py
reporting/views.py