Metadata-Version: 1.0
Name: django-reporting
Version: 0.21
Summary: Django Reporting is an application that can be integrated with the Django Admin and allows you to create dynamic reports for your models.
Home-page: https://github.com/tryolabs/django-reporting
Author: Rodrigo Herrera, Vitaliy Kucheryaviy, Marc Garcia
Author-email: rhherrera@gmail.com, ppr.vitaly@gmail.com ,garcia.marc@gmail.com
License: LGPL
Keywords: django reporting report model models
Platform: UNKNOWN
Classifier: Development Status :: 4 - Beta
Classifier: Environment :: Web Environment
Classifier: Framework :: Django
Classifier: Intended Audience :: Developers
Classifier: License :: OSI Approved :: GNU Library or Lesser General Public License (LGPL)
Classifier: Operating System :: OS Independent
Classifier: Programming Language :: Python
Classifier: Topic :: Utilities
